[{"nombreDeVerts1": 69}, {"nombreDeVerts5": 64}, {"nombreDeVerts10": 54}, {"nombreDeVerts20": 24}, {"nombreDeVerts30": 6}, {"nombreDeVerts50": 0}, {"calculs1": 54}, {"calculs2": 34}, {"calculs4": 0}, {"arithmetique1": 13}, {"arithmetique3": 0}, {"arithmetique5": 0}, {"fractions1": 0}, {"fractions4": 0}, {"fractions7": 0}, {"nombresRelatifs1": 61}, {"nombresRelatifs4": 28}, {"nombresRelatifs7": 0}, {"calculLitteral1": 0}, {"calculLitteral3": 0}, {"calculLitteral6": 0}, {"proportionnalite1": 47}, {"proportionnalite2": 29}, {"proportionnalite4": 0}, {"statistiques1": 62}, {"statistiques3": 23}, {"statistiques5": 0}, {"symetries1": 51}, {"symetries2": 35}, {"symetries4": 0}, {"perimetreEtAire1": 0}, {"perimetreEtAire2": 0}, {"perimetreEtAire4": 0}, {"volume1": 0}, {"volume2": 0}, {"volume4": 0}, {"triangles1": 59}, {"triangles2": 26}, {"triangles4": 0}, {"parallelogrammes1": 0}, {"parallelogrammes2": 0}, {"parallelogrammes3": 0}, {"espace1": 0}, {"espace2": 0}, {"espace4": 0}, {"presenterLeTravailDeSonGroupe1": 0}, {"presenterLeTravailDeSonGroupe2": 0}, {"presenterLeTravailDeSonGroupe3": 0}, {"obtenirSonBrevetDeTuteur0": 50}, {"maitriserScratch0": 0}, {"maitriserGeogebra0": 28}, {"probabilites2": 0}, {"fonctions2": 0}, {"durees2": 0}, {"angles2": 0}, {"faireUnExpose0": 0}, {"total": 72}]